{
  "name": "puppetlabs-scheduled_task",
  "version": "3.0.1",
  "author": "puppetlabs",
  "summary": "Manage scheduled tasks for Windows Server 2008 and newer operating systems.",
  "license": "Apache-2.0",
  "source": "git://github.com/puppetlabs/puppetlabs-scheduled_task",
  "project_page": "https://github.com/puppetlabs/puppetlabs-scheduled_task",
  "issues_url": "https://tickets.puppet.com/browse/MODULES",
  "dependencies": [

  ],
  "operatingsystem_support": [
    {
      "operatingsystem": "Windows",
      "operatingsystemrelease": [
        "2008",
        "2008 R2",
        "2012",
        "2012 R2",
        "2016",
        "2019",
        "7",
        "8",
        "8.1",
        "10"
      ]
    }
  ],
  "requirements": [
    {
      "name": "puppet",
      "version_requirement": ">= 6.0.0 < 8.0.0"
    }
  ],
  "pdk-version": "2.1.0",
  "template-url": "https://github.com/puppetlabs/pdk-templates.git#main",
  "template-ref": "heads/main-0-g03daa92"
}
